pynite_reporting/__init__.py
pynite_reporting/extraction.py
pynite_reporting-0.3.0.dist-info/licenses/LICENSE
pynite_reporting-0.3.0.dist-info/WHEEL
pynite_reporting-0.3.0.dist-info/METADATA
pynite_reporting-0.3.0.dist-info/RECORD
