Metadata-Version: 2.4
Name: pynite-reporting
Version: 0.3.0
Summary: pynite_reporting: A 3rd party package to aid in extracting
Author-email: Connor Ferster <connorferster@gmail.com>
Requires-Python: >=3.13
License-File: LICENSE
Requires-Dist: deepmerge>=2.0
Requires-Dist: numpy>=2.0
